setup.py
anu_r_distributions/Binomialdistribution.py
anu_r_distributions/Gaussiandistribution.py
anu_r_distributions/Generaldistribution.py
anu_r_distributions/__init__.py
anu_r_distributions.egg-info/PKG-INFO
anu_r_distributions.egg-info/SOURCES.txt
anu_r_distributions.egg-info/dependency_links.txt
anu_r_distributions.egg-info/not-zip-safe
anu_r_distributions.egg-info/top_level.txt