Metadata-Version: 1.0
Name: anu-r-distributions
Version: 1.1
Summary: Gaussian and binomial distributions
Home-page: UNKNOWN
Author: Anubhav Ranjan
Author-email: UNKNOWN
License: UNKNOWN
Platform: UNKNOWN
